config.py
constants.py
duck.py
ducktran.py
lake.py
pg.py
sql.py
ducktran-0.1.0.dist-info/WHEEL
ducktran-0.1.0.dist-info/METADATA
ducktran-0.1.0.dist-info/licenses/LICENSE
ducktran-0.1.0.dist-info/RECORD
